{
  "_note1": "KEEP THIS FILE! Check it into a version control system (VCS) like git.",
  "_note2": "ObjectBox manages crucial IDs for your object model. See docs for details.",
  "_note3": "If you have VCS merge conflicts, you must resolve them according to ObjectBox docs.",
  "entities": [
    {
      "id": "1:6710561140052512598",
      "lastPropertyId": "5:2731465705515962186",
      "name": "User",
      "properties": [
        {
          "id": "1:4225865444865609860",
          "name": "id",
          "type": 6,
          "flags": 1
        },
        {
          "id": "2:459353931806338352",
          "name": "email",
          "type": 9
        },
        {
          "id": "3:8207178628727644771",
          "name": "phone",
          "type": 9
        },
        {
          "id": "4:1652371919602603281",
          "name": "password",
          "type": 9
        },
        {
          "id": "5:2731465705515962186",
          "name": "accessToken",
          "type": 9
        }
      ],
      "relations": []
    },
    {
      "id": "2:8434588632493662923",
      "lastPropertyId": "3:4428559967660920730",
      "name": "Category",
      "properties": [
        {
          "id": "1:6785439538671170076",
          "name": "id",
          "type": 6,
          "flags": 1
        },
        {
          "id": "2:4030508031879787156",
          "name": "title",
          "type": 9
        },
        {
          "id": "3:4428559967660920730",
          "name": "icon",
          "type": 9
        }
      ],
      "relations": []
    },
    {
      "id": "3:5308136717400361620",
      "lastPropertyId": "8:6549784868475348020",
      "name": "Product",
      "properties": [
        {
          "id": "1:124710490489434657",
          "name": "id",
          "type": 6,
          "flags": 1
        },
        {
          "id": "2:3183216383332318540",
          "name": "catId",
          "type": 6
        },
        {
          "id": "3:3229071822231286605",
          "name": "title",
          "type": 9
        },
        {
          "id": "4:692543876064400945",
          "name": "unit",
          "type": 9
        },
        {
          "id": "5:9146319890237483450",
          "name": "stockAvailable",
          "type": 6
        },
        {
          "id": "6:450531800719387099",
          "name": "image",
          "type": 9
        },
        {
          "id": "7:5470407319680396238",
          "name": "price",
          "type": 8
        },
        {
          "id": "8:6549784868475348020",
          "name": "qty",
          "type": 6
        }
      ],
      "relations": []
    },
    {
      "id": "5:509171822462787999",
      "lastPropertyId": "9:5227654400572058488",
      "name": "CustomerOrder",
      "properties": [
        {
          "id": "1:246989969681041502",
          "name": "id",
          "type": 6,
          "flags": 1
        },
        {
          "id": "2:7819518234981903161",
          "name": "customerId",
          "type": 11,
          "flags": 520,
          "indexId": "2:1795654455108527773",
          "relationTarget": "User"
        },
        {
          "id": "3:5212646753811760401",
          "name": "name",
          "type": 9
        },
        {
          "id": "4:7603386471098345624",
          "name": "email",
          "type": 9
        },
        {
          "id": "5:7363144599176806433",
          "name": "phoneNumber",
          "type": 9
        },
        {
          "id": "6:8886237038893778426",
          "name": "address",
          "type": 9
        },
        {
          "id": "7:7882110451792057495",
          "name": "zip",
          "type": 9
        },
        {
          "id": "8:9017888670110827216",
          "name": "city",
          "type": 9
        },
        {
          "id": "9:5227654400572058488",
          "name": "country",
          "type": 9
        }
      ],
      "relations": [
        {
          "id": "2:5995319986259536989",
          "name": "items",
          "targetId": "3:5308136717400361620"
        }
      ]
    }
  ],
  "lastEntityId": "5:509171822462787999",
  "lastIndexId": "2:1795654455108527773",
  "lastRelationId": "2:5995319986259536989",
  "lastSequenceId": "0:0",
  "modelVersion": 5,
  "modelVersionParserMinimum": 5,
  "retiredEntityUids": [
    5898373637417550088
  ],
  "retiredIndexUids": [],
  "retiredPropertyUids": [
    3090132506391061437,
    8522163530019221265,
    5002196926875562103,
    5617315952586991891,
    2282409210486947333,
    6857460874231775031,
    6699517207167113512,
    2830924187115245760,
    6433958162379386659
  ],
  "retiredRelationUids": [],
  "version": 1
}